{
    "name": "HHKB Professional 2",
    "vendorId": "0x0853",
    "productId": "0x0101",
    "matrix": { "rows": 8, "cols": 8 },
    "customKeycodes": [{
            "name": "BLE Pair",
            "title": "[B_PAIR] Pair a new BLE device.",
            "shortName": "PAIR"
        },
        {
            "name": "BLE Device 1",
            "title": "[BLE_DEV_1] Switch BLE connection to device 1.",
            "shortName": "DEV1"
        },
        {
            "name": "BLE Device 2",
            "title": "[BLE_DEV_2] Switch BLE connection to device 2.",
            "shortName": "DEV2"
        },
        {
            "name": "BLE Device 3",
            "title": "[BLE_DEV_3] Switch BLE connection to device 3.",
            "shortName": "DEV3"
        },
        {
            "name": "BLE Device 4",
            "title": "[BLE_DEV_4] Switch BLE connection to device 4",
            "shortName": "DEV4"
        },
        {
            "name": "Clear All Bonds",
            "title": "[BLE_CLEAR] Clear all ble bonds information",
            "shortName": "CLR_A"
        },
        {
            "name": "Enter Sleep",
            "title": "[ENTER_SLEEP] Keyboard enter to sleep.",
            "shortName": "SLEEP"
        },
        {
            "name": "USB Mode",
            "title": "[REPORT_USB] Enter USB mode / \u5207\u6362\u5230USB\u6a21\u5f0f",
            "shortName": "USB"
        },
        {
            "name": "BLE Mode",
            "title": "[REPORT_BLE] Enter BLE mode.",
            "shortName": "BLE"
        },
        {
            "name": "Sleep Time +",
            "title": "[SLP_TIM_IN] Increase auto sleep time. Unit 10 min",
            "shortName": "SLEEP+"
        },
        {
            "name": "Sleep Time -",
            "title": "[SLP_TIM_DE] Decrese auto sleep time. Unit 10 min",
            "shortName": "SLEEP-"
        },
        {
            "name": "Enter DFU Mode",
            "title": "[ENTER_DFU] Enter DFU mode before OTA.",
            "shortName": "DFU"
        }
    ],
    "layouts": {
        "keymap": [
            { "name": "HHKB" },
            [
                { "c": "#aaaaaa" },
                "3,1",
                { "c": "#cccccc" },
                "3,0",
                "0,0",
                "1,0",
                "1,1",
                "2,0",
                "2,1",
                "4,0",
                "4,1",
                "6,0",
                "6,1",
                "7,0",
                "7,1",
                "5,0",
                "5,1"
            ],
            [
                { "c": "#aaaaaa", "w": 1.5 },
                "3,2",
                { "c": "#cccccc" },
                "0,1",
                "0,2",
                "1,3",
                "1,2",
                "2,3",
                "2,2",
                "4,2",
                "4,3",
                "6,2",
                "6,3",
                "7,3",
                "7,2",
                { "c": "#aaaaaa", "w": 1.5 },
                "5,2"
            ],
            [
                { "w": 1.75 },
                "3,3",
                { "c": "#cccccc" },
                "0,4",
                "0,3",
                "1,4",
                "1,5",
                "2,4",
                "2,5",
                "4,5",
                "4,4",
                "6,5",
                "6,4",
                "7,4",
                { "c": "#aaaaaa", "w": 2.25 },
                "5,3"
            ],
            [
                { "w": 2.25 },
                "3,4",
                { "c": "#cccccc" },
                "0,5",
                "0,6",
                "0,7",
                "1,6",
                "1,7",
                "2,6",
                "4,6",
                "6,6",
                "7,6",
                "7,5",
                { "c": "#aaaaaa", "w": 1.75 },
                "5,5",
                "5,4"
            ],
            [
                { "x": 1.5 },
                "3,5",
                { "w": 1.5 },
                "3,6",
                { "c": "#cccccc", "w": 6 },
                "3,7",
                { "c": "#aaaaaa", "w": 1.5 },
                "5,7",
                "5,6"
            ]
        ],
        "labels": []
    }
}